Topsis/__init__.py
Topsis/__main__.py
Topsis_Dev_102017083-1.0.1.dist-info/LICENSE
Topsis_Dev_102017083-1.0.1.dist-info/METADATA
Topsis_Dev_102017083-1.0.1.dist-info/WHEEL
Topsis_Dev_102017083-1.0.1.dist-info/entry_points.txt
Topsis_Dev_102017083-1.0.1.dist-info/top_level.txt
Topsis_Dev_102017083-1.0.1.dist-info/RECORD
