Metadata-Version: 2.1
Name: Topsis-Dev-102017083
Version: 1.0.1
Summary: topsis package for MCDM problems
Home-page: https://github.com/devgulati91/Topsis-Dev-102017083
Author: Dev Gulati
Author-email: dgulati_be20@thapar.edu
License: MIT
Classifier: License :: OSI Approved :: MIT License
Classifier: Programming Language :: Python :: 3.6
Classifier: Programming Language :: Python :: 3.7
Classifier: Programming Language :: Python :: 3.8
Classifier: Programming Language :: Python :: 3.9
Classifier: Programming Language :: Python :: 3.10
License-File: LICENSE
